.DS_Store
ngramsum/__init__.py
ngramsum/ngramsum.py
ngramsum/util.py
sumgram/__init__.py
sumgram/scratch.py
sumgram/sumgram.py
sumgram/util.py
tests/__init__.py
sumgram-1.0.4.dist-info/LICENSE
sumgram-1.0.4.dist-info/METADATA
sumgram-1.0.4.dist-info/WHEEL
sumgram-1.0.4.dist-info/entry_points.txt
sumgram-1.0.4.dist-info/top_level.txt
sumgram-1.0.4.dist-info/RECORD
